nixstrings.cp37-win32.pyd
nixstrings-0.3.0.dist-info/LICENSE
nixstrings-0.3.0.dist-info/METADATA
nixstrings-0.3.0.dist-info/WHEEL
nixstrings-0.3.0.dist-info/top_level.txt
nixstrings-0.3.0.dist-info/RECORD
