Metadata-Version: 2.1
Name: nixstrings
Version: 0.3.0
Summary: Linux/UNIX/*NIX strings command, in Cython
Home-page: https://github.com/bconstanzo/nixstrings
Download-URL: https://github.com/bconstanzo/nixstrings
Author: bconstanzo
License: MIT
Classifier: Development Status :: 4 - Beta
Classifier: Intended Audience :: Developers
Classifier: License :: OSI Approved :: MIT License
Classifier: Programming Language :: Cython
Classifier: Programming Language :: Python
Classifier: Programming Language :: Python :: 3
Classifier: Programming Language :: Python :: 3.7
Classifier: Programming Language :: Python :: 3.8
Classifier: Programming Language :: Python :: 3.9
Classifier: Programming Language :: Python :: 3.10
Classifier: Topic :: Software Development :: Libraries :: Python Modules
License-File: LICENSE
